indicai_projects/__init__.py
indicai_projects/indic_tts.py
indicai_projects/krutrim_text2text_translation.py
indicai_projects/lang_detection.py
indicai_projects/lite_tts.py
indicai_projects/sanskrit_tts.py
indicai_projects/speech2text_all.py
indicai_projects/speech2text_translation.py
indicai_projects/text2text_translation.py
indicai_projects/transliteration_rnn.py
indicai_projects/transliteration_transformer.py
indicai_projects-0.2.9.dist-info/METADATA
indicai_projects-0.2.9.dist-info/WHEEL
indicai_projects-0.2.9.dist-info/RECORD
