Metadata-Version: 2.4
Name: indicai-projects
Version: 0.2.9
Summary: IndicAI projects like ASR,TTS,Translation Etc
Author-email: dummyjenil <dummyjenil@gmail.com>
Provides-Extra: indic-tts
Requires-Dist: huggingface-hub; extra == 'indic-tts'
Requires-Dist: tts==0.22.0; extra == 'indic-tts'
Provides-Extra: krutrim-text2text-translation
Requires-Dist: ctranslate2; extra == 'krutrim-text2text-translation'
Requires-Dist: indic-nlp-library; extra == 'krutrim-text2text-translation'
Requires-Dist: mosestokenizer; extra == 'krutrim-text2text-translation'
Requires-Dist: nltk; extra == 'krutrim-text2text-translation'
Requires-Dist: sacremoses; extra == 'krutrim-text2text-translation'
Provides-Extra: lang-detection
Requires-Dist: fasttext; extra == 'lang-detection'
Requires-Dist: pandas; extra == 'lang-detection'
Requires-Dist: torch; extra == 'lang-detection'
Provides-Extra: lite-tts
Requires-Dist: soundfile; extra == 'lite-tts'
Requires-Dist: torch; extra == 'lite-tts'
Requires-Dist: transformers; extra == 'lite-tts'
Provides-Extra: sanskrit-tts
Requires-Dist: huggingface-hub; extra == 'sanskrit-tts'
Requires-Dist: numpy; extra == 'sanskrit-tts'
Requires-Dist: soundfile; extra == 'sanskrit-tts'
Requires-Dist: torch; extra == 'sanskrit-tts'
Provides-Extra: speech2text-all
Requires-Dist: huggingface-hub; extra == 'speech2text-all'
Requires-Dist: librosa; extra == 'speech2text-all'
Requires-Dist: numpy; extra == 'speech2text-all'
Requires-Dist: onnxruntime; extra == 'speech2text-all'
Provides-Extra: speech2text-translation
Requires-Dist: einops; extra == 'speech2text-translation'
Requires-Dist: numpy; extra == 'speech2text-translation'
Requires-Dist: pydub; extra == 'speech2text-translation'
Requires-Dist: sentencepiece; extra == 'speech2text-translation'
Requires-Dist: transformers; extra == 'speech2text-translation'
Provides-Extra: text2text-translation
Requires-Dist: indictranstoolkit; extra == 'text2text-translation'
Requires-Dist: sentencepiece; extra == 'text2text-translation'
Requires-Dist: torch; extra == 'text2text-translation'
Requires-Dist: transformers; extra == 'text2text-translation'
Provides-Extra: transliteration-rnn
Requires-Dist: numpy; extra == 'transliteration-rnn'
Requires-Dist: torch; extra == 'transliteration-rnn'
Provides-Extra: transliteration-transformer
Requires-Dist: fairseq-fixed; extra == 'transliteration-transformer'
Requires-Dist: indic-nlp-library-itt; extra == 'transliteration-transformer'
Requires-Dist: keras==2.15.0; extra == 'transliteration-transformer'
Requires-Dist: tensorflow==2.15.0; extra == 'transliteration-transformer'
Requires-Dist: urduhack; extra == 'transliteration-transformer'
